LICENSE
MANIFEST.in
NEWS.txt
README.txt
assignmentprint.py
setup.py
assignmentprint.egg-info/PKG-INFO
assignmentprint.egg-info/SOURCES.txt
assignmentprint.egg-info/dependency_links.txt
assignmentprint.egg-info/requires.txt
assignmentprint.egg-info/top_level.txt