Metadata-Version: 1.1
Name: assignmentprint
Version: 1.0
Summary: Pretty printer for student-submitted assignments.
Home-page: https://github.com/saffsd/assignmentprint
Author: Marco Lui
Author-email: saffsd@gmail.com
License: GPLv3
Keywords: prettyprint
Platform: UNKNOWN
Classifier: Development Status :: 4 - Beta
Classifier: Environment :: Console
Classifier: Intended Audience :: Education
Classifier: License :: OSI Approved :: GNU General Public License v3 (GPLv3)
Classifier: Operating System :: POSIX :: Linux
Classifier: Programming Language :: Python
Classifier: Topic :: Utilities
